{
  "header": "file::/parts/header-white.json",
  "footer": "file::/parts/footer.json",
  "breadcrumbs": [
    {
      "href": "/",
      "text": "Главная"
    },
    {
      "text": "Отзывы"
    }
  ],
  "sectionReviews": {
    "title": "Отзывы",
    "items": [
      {
        "lable": "Мегафон",
        "desc": "Мы рекомендуем компанию «Реюнион» как профессионального, ответственного, нацеленного на результат поставщика услуг...",
        "link": {
          "text": "Читать полностью",
          "href": "/ajax/popup-feedback-content.json",
          "popup": true,
          "type": "content"
        }
      },
      {
        "lable": "Мегафон",
        "desc": "Мы рекомендуем компанию «Реюнион» как профессионального, ответственного, нацеленного на результат поставщика услуг...",
        "link": {
          "text": "Читать полностью",
          "href": "/ajax/popup-feedback-content.json",
          "popup": true,
          "type": "content"
        }
      },
      {
        "image": {
          "sources": {
            "desktop": ["/images/user-reviews-desk.jpg"],
            "tablet": ["/images/user-reviews-tab.jpg"],
            "mobile": ["/images/user-reviews-mob.jpg"]
          },
          "alt": "Отзывы клиентов"
        },
        "title": "Чтобы начать сотрудничество",
        "link": {
          "text": "Оставьте заявку",
          "href": "/ajax/popup-feedback-reviews.json",
          "popup": true,
          "type": "callback"
        }
      },
      {
        "lable": "Мегафон",
        "desc": "Мы рекомендуем компанию «Реюнион» как профессионального, ответственного, нацеленного на результат поставщика услуг...",
        "link": {
          "text": "Читать полностью",
          "href": "/ajax/popup-feedback-content.json",
          "popup": true,
          "type": "content"
        }
      },
      {
        "lable": "Мегафон",
        "desc": "Мы рекомендуем компанию «Реюнион» как профессионального, ответственного, нацеленного на результат поставщика услуг...",
        "link": {
          "text": "Читать полностью",
          "href": "/ajax/popup-feedback-content.json",
          "popup": true,
          "type": "content"
        }
      },
      {
        "lable": "Мегафон",
        "desc": "Мы рекомендуем компанию «Реюнион» как профессионального, ответственного, нацеленного на результат поставщика услуг...",
        "link": {
          "text": "Читать полностью",
          "href": "/ajax/popup-feedback-content.json",
          "popup": true,
          "type": "content"
        }
      },
      {
        "lable": "Мегафон",
        "desc": "Мы рекомендуем компанию «Реюнион» как профессионального, ответственного, нацеленного на результат поставщика услуг...",
        "link": {
          "text": "Читать полностью",
          "href": "/ajax/popup-feedback-content.json",
          "popup": true,
          "type": "content"
        }
      },
      {
        "lable": "Мегафон",
        "desc": "Мы рекомендуем компанию «Реюнион» как профессионального, ответственного, нацеленного на результат поставщика услуг...",
        "link": {
          "text": "Читать полностью",
          "href": "/ajax/popup-feedback-content.json",
          "popup": true,
          "type": "content"
        }
      }
    ],
    "btn": {
      "text": "Загрузить еще",
      "href": "/ajax/reviews.json"
    },
    "nextPage": "/ajax/news.json"
  },
  "feedback": {
    "title": "Появились вопросы?",
    "text": "Оставьте свои контактные данные и мы свяжемся с вами в ближайшее время",
    "form": {
      "action": "/ajax/popup-success-questions.json",
      "method": "get"
    },
    "fields": [
      {
        "type": "text",
        "placeholder": "Имя",
        "name": "name",
        "validators": "required",
        "isHalf": true
      },
      {
        "type": "tel",
        "placeholder": "Телефон",
        "name": "phone",
        "validators": "required|phone",
        "isHalf": true
      },
      {
        "type": "email",
        "placeholder": "Почта",
        "name": "email",
        "validators": "required|email"
      },
      {
        "type": "textarea",
        "placeholder": "Вопрос ",
        "name": "message"
      }
    ],
    "btn": {
      "text": "Отправить",
      "type": "submit"
    },
    "politics": "Нажимая на кнопку вы соглашаетесь с <a href='/'> политикой конфиденциальности </a>",
    "image": {
      "sources": {
        "lg": ["/images/bg-feedback-lg.jpg"],
        "desktop": ["/images/bg-feedback-xl.jpg"],
        "tablet": ["/images/bg-logo.png"],
        "mobile": ["/images/bg-logo.png"]
      },
      "alt": "background"
    }
  }
}
